notexa/__init__.py
notexa/core.py
notexa-0.1.0.dist-info/licenses/LICENSE.txt
notexa-0.1.0.dist-info/METADATA
notexa-0.1.0.dist-info/WHEEL
notexa-0.1.0.dist-info/top_level.txt
notexa-0.1.0.dist-info/RECORD
